{
  "_fv": 47,
  "_type": "tool",
  "definition": {
    "toolType": "Sword",
    "renderType": 1,
    "texture": "banhammerpixel",
    "customModelName": "ban_hammer_mini_pixel:default",
    "name": "Mini Ban Hammer Pixel",
    "specialInfo": [
      "Reducing Model Lag. Also an easter egg by the way. ;)"
    ],
    "creativeTab": {
      "value": "CUSTOM:AAEItemsPixelHammers"
    },
    "harvestLevel": 1,
    "efficiency": 4.0,
    "attackSpeed": 1.0,
    "enchantability": 128000,
    "damageVsEntity": 100.0,
    "usageCount": 1500,
    "blocksAffected": [],
    "hasGlow": false,
    "repairItems": [],
    "immuneToFire": false,
    "stayInGridWhenCrafting": false,
    "damageOnCrafting": false
  }
}